a2a_schemas.py
a2a_schemas-0.1.0.dist-info/METADATA
a2a_schemas-0.1.0.dist-info/WHEEL
a2a_schemas-0.1.0.dist-info/top_level.txt
a2a_schemas-0.1.0.dist-info/RECORD
