Metadata-Version: 2.4
Name: a2a-schemas
Version: 0.1.0
Summary: A2A types for the A2A project
Requires-Python: >=3.9
